py_stats/__init__.py
py_stats/multivariate.py
py_stats/univariate.py
python_stats-1.0.1.dist-info/licenses/LICENSE
python_stats-1.0.1.dist-info/METADATA
python_stats-1.0.1.dist-info/WHEEL
python_stats-1.0.1.dist-info/top_level.txt
python_stats-1.0.1.dist-info/RECORD
