Metadata-Version: 2.4
Name: python-stats
Version: 1.0.1
Summary: A pure-Python module providing comprehensive statistics functions
Home-page: https://github.com/RanaEhtashamAli/py-stats
Author: Rana Ehtasham Ali
Author-email: Rana Ehtasham Ali <ranaehtashamali1@gmail.com>
Maintainer-email: Rana Ehtasham Ali <ranaehtashamali1@gmail.com>
License-Expression: MIT
Project-URL: Homepage, https://github.com/RanaEhtashamAli/py-stats
Project-URL: Documentation, https://github.com/RanaEhtashamAli/py-stats#readme
Project-URL: Repository, https://github.com/RanaEhtashamAli/py-stats.git
Project-URL: Bug Tracker, https://github.com/RanaEhtashamAli/py-stats/issues
Keywords: statistics,math,data-analysis,scientific-calculator
Classifier: Development Status :: 4 - Beta
Classifier: Intended Audience :: Science/Research
Classifier: Intended Audience :: Education
Classifier: Operating System :: OS Independent
Classifier: Programming Language :: Python :: 3
Classifier: Programming Language :: Python :: 3.7
Classifier: Programming Language :: Python :: 3.8
Classifier: Programming Language :: Python :: 3.9
Classifier: Programming Language :: Python :: 3.10
Classifier: Programming Language :: Python :: 3.11
Classifier: Programming Language :: Python :: 3.12
Classifier: Topic :: Scientific/Engineering :: Mathematics
Classifier: Topic :: Scientific/Engineering :: Information Analysis
Requires-Python: >=3.7
License-File: LICENSE
Requires-Dist: numpy>=1.19.0
Provides-Extra: dev
Requires-Dist: pytest>=6.0; extra == "dev"
Requires-Dist: pytest-cov>=2.0; extra == "dev"
Requires-Dist: black>=21.0; extra == "dev"
Requires-Dist: flake8>=3.8; extra == "dev"
Requires-Dist: mypy>=0.900; extra == "dev"
Dynamic: author
Dynamic: home-page
Dynamic: license-file
Dynamic: requires-python
